{
  "data": {
    "id": 1190,
    "title": "Proteção Patrimonial e Planejamento Tributário",
    "subtitle": "Administradora de Bens Imóveis Próprios",
    "summary": "Neste curso prático de proteção patrimonial e planejamento tributário, você aprenderá todos os procedimentos adequados para planejar corretamente a tributação, para fins de proteção de patrimônios. Dentre os pontos que você irá dominar estão: análise e atuação com vários tipos de clientes, administração de bens ou holdings, cronograma de trabalhos, cuidados, planejamento sucessório, doações das cotas, empresa patrimonial, contrato social, alteração contratual, ITCMD, DIMOB, aspectos societários tributários e contábeis, dentre muitos outros tópicos importantes para que você entenda o conteúdo e as táticas apresentadas, por meio de vários exemplos, e aplique na prática os conhecimentos adquiridos.",
    "banner": "https://cdn.cefis.cloud/cefiscdn/media/e0fb94d9589dfa71654bdcb38f1dd14a1728428663.jpg",
    "goals": [
      "Analisar a abertura de uma empresa com o objeto social de administração de bens imóveis próprios para a proteção patrimonial. Tendo como finalidade demonstrar as vantagens na sua constituição, nos seus aspectos societários e sucessórios e comprovando uma redução na carga tributária. \nOrientar o seu cliente para os três pilares principais para o planejamento sucessório, planejamento tributário e a proteção patrimonial. Com o objetivo de facilitar o processo de inventário da família."
    ],
    "teacher": {
      "id": 368725,
      "name": "João Alberto Teixeira",
      "avatar": "https://cdn.cefis.cloud/cefiscdn/uploads-v3/d5cb507c-904b-469f-bc5b-f42ad3c57cfa-croppedImage.jpeg"
    },
    "duration": 7333,
    "keywords": "Proteção Patrimonial e Planejamento Tributário;Proteção;Proteção Patrimonial;Planejamento Tributário",
    "certificationThreshold": null,
    "isEditing": false,
    "lessonCount": 22,
    "materialCount": 1,
    "hasMaterials": true,
    "categories": [
      2
    ],
    "watchLater": false,
    "ratingQuantity": 2148,
    "averageRating": 9.36,
    "practiceAverage": 9.35,
    "crcActive": false,
    "crcCreditHours": 5,
    "launchDate": "2019-04-22T15:28:45.000Z",
    "recordedAt": "2019-04-11T00:00:00.000Z",
    "createdAt": "2020-12-18T19:28:54.000Z"
  }
}