{
  "id": 457599,
  "title": "Subprincípio proteção da aparência",
  "position": 11,
  "duration": 96,
  "preview_url": "https://cdn.cefis.cloud/cefiscdn/media/thumbnails/e9749777-775b-4b26-9dab-6ef7d8ef2b01/sprite.vtt",
  "stream_sources": [
    {
      "quality": "sd",
      "type": "video/mp4",
      "link_secure": "https://cdn2.cefis.com.br/vod/e9749777-775b-4b26-9dab-6ef7d8ef2b01/360.mp4",
      "height": 360
    },
    {
      "quality": "sd",
      "type": "video/mp4",
      "link_secure": "https://cdn2.cefis.com.br/vod/e9749777-775b-4b26-9dab-6ef7d8ef2b01/480.mp4",
      "height": 480
    },
    {
      "quality": "hd",
      "type": "video/mp4",
      "link_secure": "https://cdn2.cefis.com.br/vod/e9749777-775b-4b26-9dab-6ef7d8ef2b01/720.mp4",
      "height": 720
    },
    {
      "quality": "hd",
      "type": "video/mp4",
      "link_secure": "https://cdn2.cefis.com.br/vod/e9749777-775b-4b26-9dab-6ef7d8ef2b01/1080.mp4",
      "height": 1080
    }
  ]
}