{
  "id": 454129,
  "title": "Lei de Interceptação de Dados",
  "position": 5,
  "duration": 372,
  "preview_url": "https://cdn.cefis.cloud/cefiscdn/media/thumbnails/e899ea6a-4cd0-4867-a171-7d5b922a55f7/sprite.vtt",
  "stream_sources": [
    {
      "quality": "sd",
      "type": "video/mp4",
      "link_secure": "https://cdn2.cefis.com.br/vod/e899ea6a-4cd0-4867-a171-7d5b922a55f7/360.mp4",
      "height": 360
    },
    {
      "quality": "sd",
      "type": "video/mp4",
      "link_secure": "https://cdn2.cefis.com.br/vod/e899ea6a-4cd0-4867-a171-7d5b922a55f7/480.mp4",
      "height": 480
    },
    {
      "quality": "hd",
      "type": "video/mp4",
      "link_secure": "https://cdn2.cefis.com.br/vod/e899ea6a-4cd0-4867-a171-7d5b922a55f7/720.mp4",
      "height": 720
    },
    {
      "quality": "hd",
      "type": "video/mp4",
      "link_secure": "https://cdn2.cefis.com.br/vod/e899ea6a-4cd0-4867-a171-7d5b922a55f7/1080.mp4",
      "height": 1080
    }
  ]
}