{
  "id": 487553,
  "title": "Opção pelo Lucro Real Trimestral - Exemplos",
  "position": 53,
  "duration": 550,
  "preview_url": "https://s3.cefis.cloud/cefiscdn/media/thumbnails/f17bd7b2-fc6a-4c00-94b3-7bafe1fff28e/sprite.vtt",
  "stream_sources": [
    {
      "quality": "sd",
      "type": "video/mp4",
      "link_secure": "https://cdn2.cefis.com.br/vod/f17bd7b2-fc6a-4c00-94b3-7bafe1fff28e/360.mp4",
      "height": 360
    },
    {
      "quality": "sd",
      "type": "video/mp4",
      "link_secure": "https://cdn2.cefis.com.br/vod/f17bd7b2-fc6a-4c00-94b3-7bafe1fff28e/480.mp4",
      "height": 480
    },
    {
      "quality": "hd",
      "type": "video/mp4",
      "link_secure": "https://cdn2.cefis.com.br/vod/f17bd7b2-fc6a-4c00-94b3-7bafe1fff28e/720.mp4",
      "height": 720
    },
    {
      "quality": "hd",
      "type": "video/mp4",
      "link_secure": "https://cdn2.cefis.com.br/vod/f17bd7b2-fc6a-4c00-94b3-7bafe1fff28e/1080.mp4",
      "height": 1080
    }
  ]
}