{
  "id": 453476,
  "title": "Sistema de governança | parte 2",
  "position": 30,
  "duration": 219,
  "preview_url": "https://cdn.cefis.cloud/cefiscdn/media/thumbnails/30d45b89-1893-43e2-92a5-9ab7fb3c38fe/sprite.vtt",
  "stream_sources": [
    {
      "quality": "sd",
      "type": "video/mp4",
      "link_secure": "https://cdn2.cefis.com.br/vod/30d45b89-1893-43e2-92a5-9ab7fb3c38fe/360.mp4",
      "height": 360
    },
    {
      "quality": "sd",
      "type": "video/mp4",
      "link_secure": "https://cdn2.cefis.com.br/vod/30d45b89-1893-43e2-92a5-9ab7fb3c38fe/480.mp4",
      "height": 480
    },
    {
      "quality": "hd",
      "type": "video/mp4",
      "link_secure": "https://cdn2.cefis.com.br/vod/30d45b89-1893-43e2-92a5-9ab7fb3c38fe/720.mp4",
      "height": 720
    },
    {
      "quality": "hd",
      "type": "video/mp4",
      "link_secure": "https://cdn2.cefis.com.br/vod/30d45b89-1893-43e2-92a5-9ab7fb3c38fe/1080.mp4",
      "height": 1080
    }
  ]
}