{
  "id": 470130,
  "title": "Resposta 2",
  "position": 8,
  "duration": 91,
  "preview_url": "https://cdn.cefis.cloud/cefiscdn/media/thumbnails/86caa243-e3e2-477b-91cf-01a676492b3f/sprite.vtt",
  "stream_sources": [
    {
      "quality": "sd",
      "type": "video/mp4",
      "link_secure": "https://cdn2.cefis.com.br/vod/86caa243-e3e2-477b-91cf-01a676492b3f/360.mp4",
      "height": 360
    },
    {
      "quality": "sd",
      "type": "video/mp4",
      "link_secure": "https://cdn2.cefis.com.br/vod/86caa243-e3e2-477b-91cf-01a676492b3f/480.mp4",
      "height": 480
    },
    {
      "quality": "hd",
      "type": "video/mp4",
      "link_secure": "https://cdn2.cefis.com.br/vod/86caa243-e3e2-477b-91cf-01a676492b3f/720.mp4",
      "height": 720
    },
    {
      "quality": "hd",
      "type": "video/mp4",
      "link_secure": "https://cdn2.cefis.com.br/vod/86caa243-e3e2-477b-91cf-01a676492b3f/1080.mp4",
      "height": 1080
    }
  ]
}