{
  "id": 474442,
  "title": "Livros fiscais",
  "position": 19,
  "duration": 264,
  "preview_url": "https://cdn.cefis.cloud/cefiscdn/media/thumbnails/7f2b3405-8e73-43be-995f-a038d67031ab/sprite.vtt",
  "stream_sources": [
    {
      "quality": "sd",
      "type": "video/mp4",
      "link_secure": "https://cdn2.cefis.com.br/vod/7f2b3405-8e73-43be-995f-a038d67031ab/360.mp4",
      "height": 360
    },
    {
      "quality": "sd",
      "type": "video/mp4",
      "link_secure": "https://cdn2.cefis.com.br/vod/7f2b3405-8e73-43be-995f-a038d67031ab/480.mp4",
      "height": 480
    },
    {
      "quality": "hd",
      "type": "video/mp4",
      "link_secure": "https://cdn2.cefis.com.br/vod/7f2b3405-8e73-43be-995f-a038d67031ab/720.mp4",
      "height": 720
    },
    {
      "quality": "hd",
      "type": "video/mp4",
      "link_secure": "https://cdn2.cefis.com.br/vod/7f2b3405-8e73-43be-995f-a038d67031ab/1080.mp4",
      "height": 1080
    }
  ]
}