{
  "id": 475347,
  "title": "Encerramento",
  "position": 19,
  "duration": 45,
  "preview_url": "https://cdn.cefis.cloud/cefiscdn/media/thumbnails/9d734440-e09f-4d46-8b09-c3fbe15d29a7/sprite.vtt",
  "stream_sources": [
    {
      "quality": "sd",
      "type": "video/mp4",
      "link_secure": "https://cdn2.cefis.com.br/vod/9d734440-e09f-4d46-8b09-c3fbe15d29a7/360.mp4",
      "height": 360
    },
    {
      "quality": "sd",
      "type": "video/mp4",
      "link_secure": "https://cdn2.cefis.com.br/vod/9d734440-e09f-4d46-8b09-c3fbe15d29a7/480.mp4",
      "height": 480
    },
    {
      "quality": "hd",
      "type": "video/mp4",
      "link_secure": "https://cdn2.cefis.com.br/vod/9d734440-e09f-4d46-8b09-c3fbe15d29a7/720.mp4",
      "height": 720
    },
    {
      "quality": "hd",
      "type": "video/mp4",
      "link_secure": "https://cdn2.cefis.com.br/vod/9d734440-e09f-4d46-8b09-c3fbe15d29a7/1080.mp4",
      "height": 1080
    }
  ]
}