{
  "id": 459308,
  "title": "Entendendo a organização  e seu contexto",
  "position": 12,
  "duration": 355,
  "preview_url": "https://cdn.cefis.cloud/cefiscdn/media/thumbnails/c44f0260-3374-42be-a738-339e3e4b05ec/sprite.vtt",
  "stream_sources": [
    {
      "quality": "sd",
      "type": "video/mp4",
      "link_secure": "https://cdn2.cefis.com.br/vod/c44f0260-3374-42be-a738-339e3e4b05ec/360.mp4",
      "height": 360
    },
    {
      "quality": "sd",
      "type": "video/mp4",
      "link_secure": "https://cdn2.cefis.com.br/vod/c44f0260-3374-42be-a738-339e3e4b05ec/480.mp4",
      "height": 480
    },
    {
      "quality": "hd",
      "type": "video/mp4",
      "link_secure": "https://cdn2.cefis.com.br/vod/c44f0260-3374-42be-a738-339e3e4b05ec/720.mp4",
      "height": 720
    },
    {
      "quality": "hd",
      "type": "video/mp4",
      "link_secure": "https://cdn2.cefis.com.br/vod/c44f0260-3374-42be-a738-339e3e4b05ec/1080.mp4",
      "height": 1080
    }
  ]
}