{
  "id": 458100,
  "title": "Encerramento do cpc 35",
  "position": 174,
  "duration": 54,
  "preview_url": "https://cdn.cefis.cloud/cefiscdn/media/thumbnails/1de1ea63-471f-428a-ad25-c42e93559c9e/sprite.vtt",
  "stream_sources": [
    {
      "quality": "sd",
      "type": "video/mp4",
      "link_secure": "https://cdn2.cefis.com.br/vod/1de1ea63-471f-428a-ad25-c42e93559c9e/360.mp4",
      "height": 360
    },
    {
      "quality": "sd",
      "type": "video/mp4",
      "link_secure": "https://cdn2.cefis.com.br/vod/1de1ea63-471f-428a-ad25-c42e93559c9e/480.mp4",
      "height": 480
    },
    {
      "quality": "hd",
      "type": "video/mp4",
      "link_secure": "https://cdn2.cefis.com.br/vod/1de1ea63-471f-428a-ad25-c42e93559c9e/720.mp4",
      "height": 720
    },
    {
      "quality": "hd",
      "type": "video/mp4",
      "link_secure": "https://cdn2.cefis.com.br/vod/1de1ea63-471f-428a-ad25-c42e93559c9e/1080.mp4",
      "height": 1080
    }
  ]
}